jinja_render/__init__.py
jinja_render/get_info_top.py
jinja_render/jinja_render.py
jinja_render-0.1.8.dist-info/entry_points.txt
jinja_render-0.1.8.dist-info/LICENSE
jinja_render-0.1.8.dist-info/WHEEL
jinja_render-0.1.8.dist-info/METADATA
jinja_render-0.1.8.dist-info/RECORD
