Metadata-Version: 2.3
Name: jinja_render
Version: 0.1.8
Summary: This module helps to render reports
Home-page: https://github.com/IslasGECI/jinja_render
Author: Ciencia de Datos • GECI
Author-email: ciencia.datos@islas.org.mx
Requires-Python: >=3.9
Classifier: License :: OSI Approved :: GNU General Public License v3 or later (GPLv3+)
Requires-Dist: jinja2
Requires-Dist: typer
